mal_tier_list_bbcode_gen/__init__.py
mal_tier_list_bbcode_gen/__main__.py
mal_tier_list_bbcode_gen/bbcodegenerator.py
mal_tier_list_bbcode_gen/cli.py
mal_tier_list_bbcode_gen/entry.py
mal_tier_list_bbcode_gen/exceptions.py
mal_tier_list_bbcode_gen/image.py
mal_tier_list_bbcode_gen/spreadsheetparser.py
mal_tier_list_bbcode_gen/tierlistgenerator.py
mal_tier_list_bbcode_gen/utils.py
mal_tier_list_bbcode_gen-2021.4.28.dist-info/LICENSE
mal_tier_list_bbcode_gen-2021.4.28.dist-info/METADATA
mal_tier_list_bbcode_gen-2021.4.28.dist-info/WHEEL
mal_tier_list_bbcode_gen-2021.4.28.dist-info/entry_points.txt
mal_tier_list_bbcode_gen-2021.4.28.dist-info/top_level.txt
mal_tier_list_bbcode_gen-2021.4.28.dist-info/RECORD
