Metadata-Version: 2.1
Name: mal-tier-list-bbcode-gen
Version: 2021.4.28
Summary: BBCode generator for MyAnimeList tier lists
Home-page: https://github.com/juliamarc/mal-tier-list-bbcode-gen
License: UNKNOWN
Platform: UNKNOWN
Classifier: License :: OSI Approved :: MIT License
Classifier: Programming Language :: Python
Classifier: Programming Language :: Python :: 3
Requires-Dist: click
Requires-Dist: bbcode
Requires-Dist: ezodf
Requires-Dist: lxml
